LICENSE
MANIFEST.in
README.md
setup.py
bin/pannote
pannote/__init__.py
pannote/core.py
pannote.egg-info/PKG-INFO
pannote.egg-info/SOURCES.txt
pannote.egg-info/dependency_links.txt
pannote.egg-info/requires.txt
pannote.egg-info/top_level.txt