Metadata-Version: 1.0
Name: pannote
Version: 0.2.0
Summary: Save notes in markdown and search them
Home-page: https://github.com/honza/pannote
Author: Honza Pokorny
Author-email: me@honza.ca
License: UNKNOWN
Platform: UNKNOWN
